XCODER/Downloader_XCODER.py
XCODER/__init__.py
XCODER-0.0.3.dist-info/METADATA
XCODER-0.0.3.dist-info/WHEEL
XCODER-0.0.3.dist-info/top_level.txt
XCODER-0.0.3.dist-info/RECORD
